phax/__init__.py
phax-0.0.0.dist-info/LICENSE
phax-0.0.0.dist-info/METADATA
phax-0.0.0.dist-info/WHEEL
phax-0.0.0.dist-info/top_level.txt
phax-0.0.0.dist-info/RECORD
